odoo8_addon_shopinvader_stripe-8.0.1.0.0.99.dev6-py3.8-nspkg.pth
odoo_addons/shopinvader_stripe/README.rst
odoo_addons/shopinvader_stripe/__init__.py
odoo_addons/shopinvader_stripe/__openerp__.py
odoo_addons/shopinvader_stripe/demo/shopinvader_payment_demo.xml
odoo_addons/shopinvader_stripe/services/__init__.py
odoo_addons/shopinvader_stripe/services/payment_service.py
odoo_addons/shopinvader_stripe/tests/__init__.py
odoo_addons/shopinvader_stripe/tests/test_payment.py
odoo8_addon_shopinvader_stripe-8.0.1.0.0.99.dev6.dist-info/METADATA
odoo8_addon_shopinvader_stripe-8.0.1.0.0.99.dev6.dist-info/WHEEL
odoo8_addon_shopinvader_stripe-8.0.1.0.0.99.dev6.dist-info/namespace_packages.txt
odoo8_addon_shopinvader_stripe-8.0.1.0.0.99.dev6.dist-info/top_level.txt
odoo8_addon_shopinvader_stripe-8.0.1.0.0.99.dev6.dist-info/RECORD
